Workbook

Sheet Справочники
A1: КАТЕГОРИИ ТОВАРОВ | E1: МЕНЕДЖЕРЫ | I1: СТАТУСЫ
A2: Код | B2: Название | C2: Комиссия | E2: Код | F2: ФИО | G2: Уровень | I2: Код | J2: Статус
A3: CAT001 | B3: Электроника | C3: 0.15 | E3: MGR001 | F3: Иванов А.С. | G3: Старший | I3: 1 | J3: Выполнен
A4: CAT002 | B4: Одежда | C4: 0.12 | E4: MGR002 | F4: Петрова М.В. | G4: Старший | I4: 2 | J4: В обработке
A5: CAT003 | B5: Бытовая техника | C5: 0.18 | E5: MGR003 | F5: Сидоров К.Н. | G5: Средний | I5: 3 | J5: Доставляется
A6: CAT004 | B6: Спорт и отдых | C6: 0.1 | E6: MGR004 | F6: Козлова Е.А. | G6: Средний | I6: 4 | J6: Отменён
A7: CAT005 | B7: Красота и здоровье | C7: 0.08 | E7: MGR005 | F7: Николаев Д.П. | G7: Младший | I7: 5 | J7: Возврат
A8: CAT006 | B8: Дом и сад | C8: 0.14 | E8: MGR006 | F8: Федорова О.И. | G8: Младший
A9: CAT007 | B9: Детские товары | C9: 0.09
A10: CAT008 | B10: Автотовары | C10: 0.16

Sheet Товары
A1: КАТАЛОГ ТОВАРОВ
A2: Артикул | B2: Название | C2: Категория | D2: Себестоимость | E2: Цена | F2: Наценка % | G2: Остаток
A3: SKU0001 | B3: Смартфон Samsung Galaxy A54 | C3: CAT001 | D3: 25000 | E3: 34990 | F3: =(E3-D3)/D3 -> 0.3996 | G3: 168
A4: SKU0002 | B4: Ноутбук ASUS VivoBook 15 | C4: CAT001 | D4: 42000 | E4: 54990 | F4: =(E4-D4)/D4 -> 0.30928571 | G4: 33
A5: SKU0003 | B5: Наушники Sony WH-1000XM4 | C5: CAT001 | D5: 18000 | E5: 24990 | F5: =(E5-D5)/D5 -> 0.38833333 | G5: 11
A6: SKU0004 | B6: Куртка мужская зимняя | C6: CAT002 | D6: 4500 | E6: 7990 | F6: =(E6-D6)/D6 -> 0.77555556 | G6: 194
A7: SKU0005 | B7: Платье женское летнее | C7: CAT002 | D7: 1800 | E7: 3490 | F7: =(E7-D7)/D7 -> 0.93888889 | G7: 75
A8: SKU0006 | B8: Кроссовки Nike Air Max | C8: CAT002 | D8: 6000 | E8: 9990 | F8: =(E8-D8)/D8 -> 0.665 | G8: 67
A9: SKU0007 | B9: Холодильник LG GA-B509 | C9: CAT003 | D9: 38000 | E9: 52990 | F9: =(E9-D9)/D9 -> 0.39447368 | G9: 62
A10: SKU0008 | B10: Стиральная машина Bosch | C10: CAT003 | D10: 32000 | E10: 44990 | F10: =(E10-D10)/D10 -> 0.4059375 | G10: 40
A11: SKU0009 | B11: Пылесос Dyson V15 | C11: CAT003 | D11: 35000 | E11: 49990 | F11: =(E11-D11)/D11 -> 0.42828571 | G11: 193
A12: SKU0010 | B12: Велосипед горный Trek | C12: CAT004 | D12: 28000 | E12: 39990 | F12: =(E12-D12)/D12 -> 0.42821429 | G12: 31
A13: SKU0011 | B13: Гантели разборные 20кг | C13: CAT004 | D13: 3500 | E13: 5990 | F13: =(E13-D13)/D13 -> 0.71142857 | G13: 178
A14: SKU0012 | B14: Палатка туристическая 4-х | C14: CAT004 | D14: 8000 | E14: 12990 | F14: =(E14-D14)/D14 -> 0.62375 | G14: 194
... A32: SKU0030 | B32: Набор косметики подарочный | C32: CAT005 | D32: 5000 | E32: 8990 | F32: =(E32-D32)/D32 -> 0.798 | G32: 144

Sheet Продажи
A1: ЖУРНАЛ ПРОДАЖ — ЯНВАРЬ 2025
A2: № Заказа | B2: Дата | C2: Клиент | D2: Артикул | E2: Товар | F2: Кол-во | G2: Цена | H2: Сумма | I2: Менеджер | J2: Регион | K2: Статус
A3: ORD-2025001 | B3: 45659 | C3: Петров К.С. | D3: SKU0003 | E3: Наушники Sony WH-1000XM4 | F3: 4 | G3: 24990 | H3: =F3*G3 -> 99960 | I3: MGR003 | J3: Санкт-Петербург | K3: Выполнен
A4: ORD-2025002 | B4: 45670 | C4: ООО "Альфа" | D4: SKU0018 | E4: Газонокосилка электрическ... | F4: 3 | G4: 18990 | H4: =F4*G4 -> 56970 | I4: MGR003 | J4: Москва | K4: Выполнен
A5: ORD-2025003 | B5: 45662 | C5: Соловьёв Р.А. | D5: SKU0018 | E5: Газонокосилка электрическ... | F5: 3 | G5: 18990 | H5: =F5*G5 -> 56970 | I5: MGR006 | J5: Екатеринбург | K5: Выполнен
A6: ORD-2025004 | B6: 45658 | C6: Павлова Н.Д. | D6: SKU0025 | E6: Планшет iPad Air | F6: 1 | G6: 64990 | H6: =F6*G6 -> 64990 | I6: MGR005 | J6: Челябинск | K6: Выполнен
A7: ORD-2025005 | B7: 45658 | C7: Соловьёв Р.А. | D7: SKU0024 | E7: Компрессор автомобильный | F7: 4 | G7: 4990 | H7: =F7*G7 -> 19960 | I7: MGR001 | J7: Москва | K7: Выполнен
A8: ORD-2025006 | B8: 45679 | C8: Лебедев Д.А. | D8: SKU0005 | E8: Платье женское летнее | F8: 1 | G8: 3490 | H8: =F8*G8 -> 3490 | I8: MGR003 | J8: Челябинск | K8: Выполнен
A9: ORD-2025007 | B9: 45673 | C9: Петров К.С. | D9: SKU0016 | E9: Диван угловой | F9: 1 | G9: 54990 | H9: =F9*G9 -> 54990 | I9: MGR003 | J9: Нижний Новгород | K9: Возврат
A10: ORD-2025008 | B10: 45683 | C10: ООО "ТехноСервис" | D10: SKU0007 | E10: Холодильник LG GA-B509 | F10: 5 | G10: 52990 | H10: =F10*G10 -> 264950 | I10: MGR006 | J10: Ростов-на-Дону | K10: Выполнен
A11: ORD-2025009 | B11: 45683 | C11: Соловьёв Р.А. | D11: SKU0001 | E11: Смартфон Samsung Galaxy A... | F11: 4 | G11: 34990 | H11: =F11*G11 -> 139960 | I11: MGR006 | J11: Ростов-на-Дону | K11: Доставляется
A12: ORD-2025010 | B12: 45679 | C12: ООО "Альфа" | D12: SKU0021 | E12: Автокресло детское | F12: 5 | G12: 13990 | H12: =F12*G12 -> 69950 | I12: MGR004 | J12: Ростов-на-Дону | K12: Доставляется
A13: ORD-2025011 | B13: 45669 | C13: ИП Королёв | D13: SKU0002 | E13: Ноутбук ASUS VivoBook 15 | F13: 2 | G13: 54990 | H13: =F13*G13 -> 109980 | I13: MGR006 | J13: Санкт-Петербург | K13: Отменён
A14: ORD-2025012 | B14: 45679 | C14: Петров К.С. | D14: SKU0006 | E14: Кроссовки Nike Air Max | F14: 3 | G14: 9990 | H14: =F14*G14 -> 29970 | I14: MGR003 | J14: Ростов-на-Дону | K14: Доставляется
... A152: ORD-2025150 | B152: 45676 | C152: Зайцев С.Г. | D152: SKU0018 | E152: Газонокосилка электрическ... | F152: 1 | G152: 18990 | H152: =F152*G152 -> 18990 | I152: MGR003 | J152: Самара | K152: Выполнен

Sheet Дашборд
A1: 📊 АНАЛИТИЧЕСКИЙ ДАШБОРД — ЯНВАРЬ 2025
A3: ОБЩАЯ ВЫРУЧКА | C3: ЗАКАЗОВ (ВЫПОЛНЕНО) | E3: СРЕДНИЙ ЧЕК | G3: КОНВЕРСИЯ | I3: ВОЗВРАТЫ
A4: =SUMIF(Продажи!K3:K152,"Выполнен",Продажи!H3:H152) -> 5427870 | C4: =COUNTIF(Продажи!K3:K152,"Выполнен") -> 76 | E4: =AVERAGEIF(Продажи!K3:K152,"Выполнен",Продажи!H3:H152) -> 71419.342 | G4: =COUNTIF(Продажи!K3:K152,"Выполнен")/COUNTA(Продажи!K3:K152) -> 0.50666667 | I4: =COUNTIF(Продажи!K3:K152,"Возврат")+COUNTIF(Продажи!K3:K152,"Отменён") -> 26
A8: 📍 ПРОДАЖИ ПО РЕГИОНАМ | E8: 👤 ЭФФЕКТИВНОСТЬ МЕНЕДЖЕРОВ
A9: Регион | B9: Выручка | C9: Заказов | E9: Код | F9: Выручка | G9: Заказов | H9: Ср. чек
A10: Москва | B10: =SUMIFS(Продажи!H3:H152,Продажи!J3:J152,A10,Продажи!K3:K152,"Выполнен") -> 491730 | C10: =COUNTIFS(Продажи!J3:J152,A10,Продажи!K3:K152,"Выполнен") -> 8 | E10: MGR001 | F10: =SUMIFS(Продажи!H3:H152,Продажи!I3:I152,E10,Продажи!K3:K152,"Выполнен") -> 1316530 | G10: =COUNTIFS(Продажи!I3:I152,E10,Продажи!K3:K152,"Выполнен") -> 16 | H10: =IFERROR(F10/G10,0) -> 82283.125
A11: Санкт-Петербург | B11: =SUMIFS(Продажи!H3:H152,Продажи!J3:J152,A11,Продажи!K3:K152,"Выполнен") -> 586730 | C11: =COUNTIFS(Продажи!J3:J152,A11,Продажи!K3:K152,"Выполнен") -> 9 | E11: MGR002 | F11: =SUMIFS(Продажи!H3:H152,Продажи!I3:I152,E11,Продажи!K3:K152,"Выполнен") -> 798130 | G11: =COUNTIFS(Продажи!I3:I152,E11,Продажи!K3:K152,"Выполнен") -> 13 | H11: =IFERROR(F11/G11,0) -> 61394.615
A12: Новосибирск | B12: =SUMIFS(Продажи!H3:H152,Продажи!J3:J152,A12,Продажи!K3:K152,"Выполнен") -> 394860 | C12: =COUNTIFS(Продажи!J3:J152,A12,Продажи!K3:K152,"Выполнен") -> 8 | E12: MGR003 | F12: =SUMIFS(Продажи!H3:H152,Продажи!I3:I152,E12,Продажи!K3:K152,"Выполнен") -> 917180 | G12: =COUNTIFS(Продажи!I3:I152,E12,Продажи!K3:K152,"Выполнен") -> 13 | H12: =IFERROR(F12/G12,0) -> 70552.308
A13: Екатеринбург | B13: =SUMIFS(Продажи!H3:H152,Продажи!J3:J152,A13,Продажи!K3:K152,"Выполнен") -> 335810 | C13: =COUNTIFS(Продажи!J3:J152,A13,Продажи!K3:K152,"Выполнен") -> 6 | E13: MGR004 | F13: =SUMIFS(Продажи!H3:H152,Продажи!I3:I152,E13,Продажи!K3:K152,"Выполнен") -> 685640 | G13: =COUNTIFS(Продажи!I3:I152,E13,Продажи!K3:K152,"Выполнен") -> 12 | H13: =IFERROR(F13/G13,0) -> 57136.667
A14: Казань | B14: =SUMIFS(Продажи!H3:H152,Продажи!J3:J152,A14,Продажи!K3:K152,"Выполнен") -> 1024730 | C14: =COUNTIFS(Продажи!J3:J152,A14,Продажи!K3:K152,"Выполнен") -> 9 | E14: MGR005 | F14: =SUMIFS(Продажи!H3:H152,Продажи!I3:I152,E14,Продажи!K3:K152,"Выполнен") -> 527320 | G14: =COUNTIFS(Продажи!I3:I152,E14,Продажи!K3:K152,"Выполнен") -> 8 | H14: =IFERROR(F14/G14,0) -> 65915
A15: Нижний Новгород | B15: =SUMIFS(Продажи!H3:H152,Продажи!J3:J152,A15,Продажи!K3:K152,"Выполнен") -> 173850 | C15: =COUNTIFS(Продажи!J3:J152,A15,Продажи!K3:K152,"Выполнен") -> 6 | E15: MGR006 | F15: =SUMIFS(Продажи!H3:H152,Продажи!I3:I152,E15,Продажи!K3:K152,"Выполнен") -> 1183070 | G15: =COUNTIFS(Продажи!I3:I152,E15,Продажи!K3:K152,"Выполнен") -> 14 | H15: =IFERROR(F15/G15,0) -> 84505
A16: Челябинск | B16: =SUMIFS(Продажи!H3:H152,Продажи!J3:J152,A16,Продажи!K3:K152,"Выполнен") -> 314810 | C16: =COUNTIFS(Продажи!J3:J152,A16,Продажи!K3:K152,"Выполнен") -> 9
A17: Самара | B17: =SUMIFS(Продажи!H3:H152,Продажи!J3:J152,A17,Продажи!K3:K152,"Выполнен") -> 606780 | C17: =COUNTIFS(Продажи!J3:J152,A17,Продажи!K3:K152,"Выполнен") -> 7
A18: Ростов-на-Дону | B18: =SUMIFS(Продажи!H3:H152,Продажи!J3:J152,A18,Продажи!K3:K152,"Выполнен") -> 1254680 | C18: =COUNTIFS(Продажи!J3:J152,A18,Продажи!K3:K152,"Выполнен") -> 11
A19: Уфа | B19: =SUMIFS(Продажи!H3:H152,Продажи!J3:J152,A19,Продажи!K3:K152,"Выполнен") -> 243890 | C19: =COUNTIFS(Продажи!J3:J152,A19,Продажи!K3:K152,"Выполнен") -> 3
A22: 🏷️ ПРОДАЖИ ПО КАТЕГОРИЯМ | F22: 📋 СТАТУСЫ ЗАКАЗОВ
A23: Категория | B23: Код | C23: Выручка | D23: Доля % | F23: Статус | G23: Кол-во | H23: Доля
A24: Электроника | B24: CAT001 | C24: 1205632 | D24: =C24/SUM($C$24:$C$31) -> 0.089912497 | F24: Выполнен | G24: =COUNTIF(Продажи!K3:K152,F24) -> 76 | H24: =G24/SUM($G$24:$G$28) -> 0.50666667
A25: Одежда | B25: CAT002 | C25: 1944061 | D25: =C25/SUM($C$24:$C$31) -> 0.14498237 | F25: В обработке | G25: =COUNTIF(Продажи!K3:K152,F25) -> 12 | H25: =G25/SUM($G$24:$G$28) -> 0.08
A26: Бытовая техника | B26: CAT003 | C26: 2965859 | D26: =C26/SUM($C$24:$C$31) -> 0.22118506 | F26: Доставляется | G26: =COUNTIF(Продажи!K3:K152,F26) -> 36 | H26: =G26/SUM($G$24:$G$28) -> 0.24
A27: Спорт и отдых | B27: CAT004 | C27: 1038362 | D27: =C27/SUM($C$24:$C$31) -> 0.077437991 | F27: Отменён | G27: =COUNTIF(Продажи!K3:K152,F27) -> 11 | H27: =G27/SUM($G$24:$G$28) -> 0.073333333
A28: Красота и здоровье | B28: CAT005 | C28: 1086088 | D28: =C28/SUM($C$24:$C$31) -> 0.080997256 | F28: Возврат | G28: =COUNTIF(Продажи!K3:K152,F28) -> 15 | H28: =G28/SUM($G$24:$G$28) -> 0.1
A29: Дом и сад | B29: CAT006 | C29: 1776367 | D29: =C29/SUM($C$24:$C$31) -> 0.13247624
A30: Детские товары | B30: CAT007 | C30: 2244633 | D30: =C30/SUM($C$24:$C$31) -> 0.16739814
A31: Автотовары | B31: CAT008 | C31: 1147946 | D31: =C31/SUM($C$24:$C$31) -> 0.085610445

Sheet Топ товаров
A1: 🏆 ТОП-10 ТОВАРОВ ПО ПРОДАЖАМ
A2: Место | B2: Артикул | C2: Название | D2: Продано шт. | E2: Выручка | F2: Рейтинг
A3: 1 | B3: SKU0001 | C3: Смартфон Samsung Galaxy A54 | D3: 45 | E3: 1574550 | F3: ⭐⭐⭐⭐⭐
A4: 2 | B4: SKU0002 | C4: Ноутбук ASUS VivoBook 15 | D4: 38 | E4: 2089620 | F4: ⭐⭐⭐⭐⭐
A5: 3 | B5: SKU0007 | C5: Холодильник LG GA-B509 | D5: 32 | E5: 1695680 | F5: ⭐⭐⭐⭐
A6: 4 | B6: SKU0026 | C6: Телевизор LG OLED 55" | D6: 28 | E6: 2799720 | F6: ⭐⭐⭐⭐⭐
A7: 5 | B7: SKU0006 | C7: Кроссовки Nike Air Max | D7: 52 | E7: 519480 | F7: ⭐⭐⭐⭐
A8: 6 | B8: SKU0010 | C8: Велосипед горный Trek | D8: 24 | E8: 959760 | F8: ⭐⭐⭐⭐
A9: 7 | B9: SKU0025 | C9: Планшет iPad Air | D9: 22 | E9: 1429780 | F9: ⭐⭐⭐⭐⭐
A10: 8 | B10: SKU0008 | C10: Стиральная машина Bosch | D10: 20 | E10: 899800 | F10: ⭐⭐⭐⭐
A11: 9 | B11: SKU0004 | C11: Куртка мужская зимняя | D11: 48 | E11: 383520 | F11: ⭐⭐⭐
A12: 10 | B12: SKU0016 | C12: Диван угловой | D12: 15 | E12: 824850 | F12: ⭐⭐⭐⭐
